{
  "required": true,
  "minVersion": "0.8",
  "package": "com.maximumg9.shadow.mixins",
  "compatibilityLevel": "JAVA_21",
  "mixins": [
    "MinecraftServerMixin",
    "abilities.shadow.EntityTrackerMixin",
    "abilities.shadow.LivingEntityMixin",
    "abilities.shadow.TridentEntityMixin",
    "abilities.villager.PersistentProjectileMixin",
    "abilities.villager.lifelink.LivingEntityMixin",
    "abilities.villager.lifeweaver_rework.LivingEntityMixin",
    "commands.CommandManagerMixin",
    "glowing.EntityTrackerEntryMixin",
    "glowing.EntityTrackerMixin",
    "items.EntityEquipmentUpdateS2CPacketMixin",
    "items.ItemStackMixin",
    "items.LivingEntityMixin",
    "items.ScreenHandlerMixin",
    "items.ServerPlayerEntityMixin",
    "items.SlotMixin",
    "mechanics.AdvancementFrameMixin",
    "mechanics.DragonDeathMixin",
    "mechanics.MessageCommandMixin",
    "mechanics.PlayerAdvancementTrackerMixin",
    "mechanics.ServerPlayerEntityMixin",
    "mechanics.ServerPlayerInteractionManagerMixin",
    "mechanics.ServerPlayNetworkHandlerMixin",
    "mechanics.ServerWorldMixin",
    "mechanics.StrongholdStructureMixin",
    "mechanics.StrongholdStructureMixin$PortalRoomMixin",
    "mechanics.StrongholdStructureMixin$StrongholdPieceMixin",
    "mechanics.StrongholdStructureMixin$StrongholdStartMixin",
    "ncr.ChatCommandSignedC2SPacketMixin",
    "ncr.ChatMessageC2SPacketMixin",
    "ncr.DedicatedServerMixin",
    "ncr.PlayerSessionC2SPacketMixin",
    "ncr.ServerCommonNetworkHandlerMixin"
  ],
  "injectors": {
    "defaultRequire": 1
  }
}
